numbaml/__init__.py
numbaml/dbml/__init__.py
numbaml/dbml/ridge_causal_inference.py
numbaml/linear_model/__init__.py
numbaml/linear_model/base_model.py
numbaml/linear_model/confidence_intervals.py
numbaml/linear_model/fit.py
numbaml/linear_model/linear_regression.py
numbaml/linear_model/model_selection.py
numbaml/linear_model/predict.py
numbaml/linear_model/ridge.py
numbaml/metrics/__init__.py
numbaml/metrics/metrics.py
NumbaML-1.0.21.dist-info/METADATA
NumbaML-1.0.21.dist-info/WHEEL
NumbaML-1.0.21.dist-info/top_level.txt
NumbaML-1.0.21.dist-info/RECORD
