Metadata-Version: 2.1
Name: NumbaML
Version: 1.0.21
Summary: Linear regression with Numba
Home-page: https://github.com/jcatankard/NumbaML
Author: Josh Tankard
Requires-Dist: numba
Requires-Dist: numpy
Requires-Dist: scipy
